{
    "modulename": "Postpaid Ana Menü", 
    "enddate": "", 
    "beginddate": "2018-05-10", 
    "totalcall": 31912, 
    "totaldisconnect": 1028, 
    "dtmf": "", 
    "totalhangup": 10632, 
    "totalagent": 20252, 
    "nodedesctag": "PostPaid Ana Menu", 
    "totalperc": 53.54362416107382, 
    "disconnectperc": 46.706042707860064, 
    "details": [
        {
            "modulename": "Fatura Ana Menü", 
            "enddate": "", 
            "beginddate": "2018-05-10", 
            "totalcall": 7034, 
            "totaldisconnect": 235, 
            "dtmf": "1", 
            "totalhangup": 2655, 
            "totalagent": 4144, 
            "nodedesctag": "KK ile Fatura Ödeme Postpaid Alt Menusu", 
            "totalperc": 22.04186512910504, 
            "disconnectperc": 22.859922178988327, 
            "details": [
                {
                    "modulename": "Fatura Ödeme", 
                    "enddate": "", 
                    "beginddate": "2018-05-10", 
                    "totalcall": 1065, 
                    "totaldisconnect": 130, 
                    "dtmf": "1", 
                    "totalhangup": 838, 
                    "totalagent": 97, 
                    "nodedesctag": "KK ie FaturaÖdeme Alt Menu Fatura Ödeme", 
                    "totalperc": 15.140744953085017, 
                    "disconnectperc": 55.319148936170215, 
                    "details": [
                        {
                            "modulename": "Faturası Olmayanlar", 
                            "enddate": "", 
                            "beginddate": "2018-05-10", 
                            "totalcall": 406, 
                            "totaldisconnect": 50, 
                            "dtmf": "", 
                            "totalhangup": 294, 
                            "totalagent": 62, 
                            "nodedesctag": "KK Fatura Odeme - Ödenmemiş fatura yok", 
                            "totalperc": 38.12206572769953, 
                            "disconnectperc": 38.46153846153847, 
                            "details": [], 
                            "agentperc": 63.91752577319587, 
                            "hangupperc": 35.08353221957041
                        }, 
                        {
                            "modulename": "Faturası Olanlar", 
                            "enddate": "", 
                            "beginddate": "2018-05-10", 
                            "totalcall": 659, 
                            "totaldisconnect": 57, 
                            "dtmf": "", 
                            "totalhangup": 580, 
                            "totalagent": 22, 
                            "nodedesctag": "KK Fatura Odeme - Ödenmemiş 1 fatura var || KK Fatura Odeme - Ödenmemiş 1 den fazla fatura var", 
                            "totalperc": 61.87793427230047, 
                            "disconnectperc": 43.84615384615385, 
                            "details": [
                                {
                                    "modulename": "İşlem Yapanlar", 
                                    "enddate": "", 
                                    "beginddate": "2018-05-10", 
                                    "totalcall": 405, 
                                    "totaldisconnect": 8, 
                                    "dtmf": "", 
                                    "totalhangup": 375, 
                                    "totalagent": 22, 
                                    "nodedesctag": "KK ile Fatura Odeme UnragPay Menu", 
                                    "totalperc": 61.45675265553869, 
                                    "disconnectperc": 14.035087719298245, 
                                    "details": [], 
                                    "agentperc": 100.0, 
                                    "hangupperc": 64.65517241379311
                                }, 
                                {
                                    "modulename": "İşlem Yapmayanlar", 
                                    "enddate": "", 
                                    "beginddate": "2018-05-10", 
                                    "totalcall": 659, 
                                    "totaldisconnect": 57, 
                                    "dtmf": "", 
                                    "totalhangup": 580, 
                                    "totalagent": 22, 
                                    "nodedesctag": "", 
                                    "totalperc": 100.0, 
                                    "disconnectperc": 100.0, 
                                    "details": [], 
                                    "agentperc": 100.0, 
                                    "hangupperc": 100.0
                                }, 
                                {
                                    "modulename": "Diğer (Anamenü,hangup, vs)", 
                                    "enddate": "", 
                                    "beginddate": "2018-05-10", 
                                    "totalcall": 659, 
                                    "totaldisconnect": 57, 
                                    "dtmf": "", 
                                    "totalhangup": 580, 
                                    "totalagent": 22, 
                                    "nodedesctag": "", 
                                    "totalperc": 100.0, 
                                    "disconnectperc": 100.0, 
                                    "details": [], 
                                    "agentperc": 100.0, 
                                    "hangupperc": 100.0
                                }
                            ], 
                            "agentperc": 22.68041237113402, 
                            "hangupperc": 69.21241050119332
                        }
                    ], 
                    "agentperc": 2.3407335907335907, 
                    "hangupperc": 31.563088512241055
                }, 
                {
                    "modulename": "Fatura Detaylar", 
                    "enddate": "", 
                    "beginddate": "2018-05-10", 
                    "totalcall": 1835, 
                    "totaldisconnect": 58, 
                    "dtmf": "2", 
                    "totalhangup": 1293, 
                    "totalagent": 484, 
                    "nodedesctag": "KK ie FaturaÖdeme Alt Menu FaturaDetaylar", 
                    "totalperc": 26.087574637475118, 
                    "disconnectperc": 24.680851063829788, 
                    "details": [
                        {
                            "modulename": "Faturası Olmayanlar", 
                            "enddate": "", 
                            "beginddate": "2018-05-10", 
                            "totalcall": 735, 
                            "totaldisconnect": 20, 
                            "dtmf": "", 
                            "totalhangup": 494, 
                            "totalagent": 221, 
                            "nodedesctag": "FaturaDetaylar Fatura yok bilgi anonsu", 
                            "totalperc": 40.05449591280654, 
                            "disconnectperc": 34.48275862068966, 
                            "details": [], 
                            "agentperc": 45.66115702479338, 
                            "hangupperc": 38.20572312451663
                        }, 
                        {
                            "modulename": "Faturası Olanlar", 
                            "enddate": "", 
                            "beginddate": "2018-05-10", 
                            "totalcall": 1087, 
                            "totaldisconnect": 37, 
                            "dtmf": "", 
                            "totalhangup": 794, 
                            "totalagent": 256, 
                            "nodedesctag": "FaturaDetaylar Fatura bilgi anonsu", 
                            "totalperc": 59.237057220708444, 
                            "disconnectperc": 63.793103448275865, 
                            "details": [
                                {
                                    "modulename": "Fatura Ödemeye Gidenler", 
                                    "enddate": "", 
                                    "beginddate": "2018-05-10", 
                                    "totalcall": 0, 
                                    "totaldisconnect": 0, 
                                    "dtmf": "", 
                                    "totalhangup": 0, 
                                    "totalagent": 0, 
                                    "nodedesctag": "FaturaDetaylar Payment Success Log", 
                                    "totalperc": 0.0, 
                                    "disconnectperc": 0.0, 
                                    "details": [], 
                                    "agentperc": 0.0, 
                                    "hangupperc": 0.0
                                }, 
                                {
                                    "modulename": "Sms ile Detay İsteyenler", 
                                    "enddate": "", 
                                    "beginddate": "2018-05-10", 
                                    "totalcall": 135, 
                                    "totaldisconnect": 4, 
                                    "dtmf": "", 
                                    "totalhangup": 95, 
                                    "totalagent": 36, 
                                    "nodedesctag": "FaturaDetaylar Fatura detayı bilgi anonsu", 
                                    "totalperc": 12.419503219871206, 
                                    "disconnectperc": 10.81081081081081, 
                                    "details": [], 
                                    "agentperc": 14.0625, 
                                    "hangupperc": 11.964735516372796
                                }, 
                                {
                                    "modulename": "Diğer (Anamenü, Hangup, vb)", 
                                    "enddate": "", 
                                    "beginddate": "2018-05-10", 
                                    "totalcall": 1087, 
                                    "totaldisconnect": 37, 
                                    "dtmf": "", 
                                    "totalhangup": 794, 
                                    "totalagent": 256, 
                                    "nodedesctag": "", 
                                    "totalperc": 100.0, 
                                    "disconnectperc": 100.0, 
                                    "details": [], 
                                    "agentperc": 100.0, 
                                    "hangupperc": 100.0
                                }
                            ], 
                            "agentperc": 52.892561983471076, 
                            "hangupperc": 61.40757927300851
                        }
                    ], 
                    "agentperc": 11.67953667953668, 
                    "hangupperc": 48.70056497175141
                }, 
                {
                    "modulename": "Güncel Fatura", 
                    "enddate": "", 
                    "beginddate": "2018-05-10", 
                    "totalcall": 864, 
                    "totaldisconnect": 25, 
                    "dtmf": "3", 
                    "totalhangup": 487, 
                    "totalagent": 352, 
                    "nodedesctag": "KK ie FaturaÖdeme Alt Menu  GuncelFatura", 
                    "totalperc": 12.283195905601364, 
                    "disconnectperc": 10.638297872340425, 
                    "details": [], 
                    "agentperc": 8.494208494208493, 
                    "hangupperc": 18.342749529190208
                }, 
                {
                    "modulename": "E-FaturaServisleri", 
                    "enddate": "", 
                    "beginddate": "2018-05-10", 
                    "totalcall": 236, 
                    "totaldisconnect": 26, 
                    "dtmf": "4", 
                    "totalhangup": 162, 
                    "totalagent": 48, 
                    "nodedesctag": "KK ie FaturaÖdeme Alt Menu  E-FaturaServisleri", 
                    "totalperc": 3.3551322149559284, 
                    "disconnectperc": 11.063829787234042, 
                    "details": [
                        {
                            "modulename": "E Fatura Aktivasyon", 
                            "enddate": "", 
                            "beginddate": "2018-05-10", 
                            "totalcall": 106, 
                            "totaldisconnect": 15, 
                            "dtmf": "1", 
                            "totalhangup": 84, 
                            "totalagent": 7, 
                            "nodedesctag": "Postpaid Menu EFaturaMenuFaturaServisleri", 
                            "totalperc": 44.91525423728814, 
                            "disconnectperc": 57.692307692307686, 
                            "details": [], 
                            "agentperc": 14.583333333333334, 
                            "hangupperc": 51.85185185185185
                        }, 
                        {
                            "modulename": "Otomatik Ödeme Talimatı", 
                            "enddate": "", 
                            "beginddate": "2018-05-10", 
                            "totalcall": 27, 
                            "totaldisconnect": 3, 
                            "dtmf": "2", 
                            "totalhangup": 21, 
                            "totalagent": 3, 
                            "nodedesctag": "E-Fatura Servisleri Alt Menu Otamatik Odeme Talimat", 
                            "totalperc": 11.440677966101696, 
                            "disconnectperc": 11.538461538461538, 
                            "details": [], 
                            "agentperc": 6.25, 
                            "hangupperc": 12.962962962962962
                        }, 
                        {
                            "modulename": "Fatura Üst Limit", 
                            "enddate": "", 
                            "beginddate": "2018-05-10", 
                            "totalcall": 25, 
                            "totaldisconnect": 0, 
                            "dtmf": "3", 
                            "totalhangup": 22, 
                            "totalagent": 3, 
                            "nodedesctag": "Postpaid Menu FUS", 
                            "totalperc": 10.59322033898305, 
                            "disconnectperc": 0.0, 
                            "details": [], 
                            "agentperc": 6.25, 
                            "hangupperc": 13.580246913580247
                        }
                    ], 
                    "agentperc": 1.1583011583011582, 
                    "hangupperc": 6.101694915254238
                }, 
                {
                    "modulename": "Numara Değişikliği", 
                    "enddate": "", 
                    "beginddate": "2018-05-10", 
                    "totalcall": 84, 
                    "totaldisconnect": 11, 
                    "dtmf": "5", 
                    "totalhangup": 17, 
                    "totalagent": 56, 
                    "nodedesctag": "KK ie FaturaÖdeme Alt Menu  Numara Degişikligi", 
                    "totalperc": 1.194199601933466, 
                    "disconnectperc": 4.680851063829787, 
                    "details": [
                        {
                            "modulename": "Numara Değişikliği Bilgi Alma", 
                            "enddate": "", 
                            "beginddate": "2018-05-10", 
                            "totalcall": 29, 
                            "totaldisconnect": 3, 
                            "dtmf": "1", 
                            "totalhangup": 6, 
                            "totalagent": 20, 
                            "nodedesctag": "Numara Değişikliği Bilgi Anonsu", 
                            "totalperc": 34.523809523809526, 
                            "disconnectperc": 27.27272727272727, 
                            "details": [], 
                            "agentperc": 35.714285714285715, 
                            "hangupperc": 35.294117647058826
                        }, 
                        {
                            "modulename": "Numara Değişikliği İşlemi", 
                            "enddate": "", 
                            "beginddate": "2018-05-10", 
                            "totalcall": 10, 
                            "totaldisconnect": 4, 
                            "dtmf": "2", 
                            "totalhangup": 4, 
                            "totalagent": 2, 
                            "nodedesctag": "Numara Degisikligi Bilgi Anonsu", 
                            "totalperc": 11.904761904761903, 
                            "disconnectperc": 36.36363636363637, 
                            "details": [], 
                            "agentperc": 3.571428571428571, 
                            "hangupperc": 23.52941176470588
                        }
                    ], 
                    "agentperc": 1.3513513513513513, 
                    "hangupperc": 0.64030131826742
                }, 
                {
                    "modulename": "Geçmiş Çağrı Detayları", 
                    "enddate": "", 
                    "beginddate": "2018-05-10", 
                    "totalcall": 245, 
                    "totaldisconnect": 8, 
                    "dtmf": "6", 
                    "totalhangup": 158, 
                    "totalagent": 79, 
                    "nodedesctag": "KK ie FaturaÖdeme Alt Menu GeçmişÇagriDetaylari", 
                    "totalperc": 3.4830821723059424, 
                    "disconnectperc": 3.404255319148936, 
                    "details": [], 
                    "agentperc": 1.9063706563706564, 
                    "hangupperc": 5.951035781544256
                }, 
                {
                    "modulename": "MT Transfer", 
                    "enddate": "", 
                    "beginddate": "2018-05-10", 
                    "totalcall": 3542, 
                    "totaldisconnect": 1, 
                    "dtmf": "0", 
                    "totalhangup": 9, 
                    "totalagent": 3532, 
                    "nodedesctag": "KK ile Fatura Ödeme Postpaid Alt Menusu , MT Transfer", 
                    "totalperc": 50.35541654819448, 
                    "disconnectperc": 0.425531914893617, 
                    "details": [], 
                    "agentperc": 85.23166023166023, 
                    "hangupperc": 0.3389830508474576
                }
            ], 
            "agentperc": 20.46217657515307, 
            "hangupperc": 24.971783295711063
        }, 
        {
            "modulename": "Tarife Ana Menü", 
            "enddate": "", 
            "beginddate": "2018-05-10", 
            "totalcall": 9968, 
            "totaldisconnect": 82, 
            "dtmf": "2", 
            "totalhangup": 2841, 
            "totalagent": 7045, 
            "nodedesctag": "Tarife Menu Postpaid Alt Menusu", 
            "totalperc": 31.23589872148408, 
            "disconnectperc": 7.976653696498054, 
            "details": [
                {
                    "modulename": "Tarife İşlemleri", 
                    "enddate": "", 
                    "beginddate": "2018-05-10", 
                    "totalcall": 1620, 
                    "totaldisconnect": 7, 
                    "dtmf": "1", 
                    "totalhangup": 73, 
                    "totalagent": 1540, 
                    "nodedesctag": "Tarife Alt MenuTarife Islemleri", 
                    "totalperc": 16.252006420545747, 
                    "disconnectperc": 8.536585365853659, 
                    "details": [
                        {
                            "modulename": "Tarifeler Hakkında Bilgi Alma", 
                            "enddate": "", 
                            "beginddate": "2018-05-10", 
                            "totalcall": 4, 
                            "totaldisconnect": 0, 
                            "dtmf": "1", 
                            "totalhangup": 2, 
                            "totalagent": 2, 
                            "nodedesctag": "Dinamik Menü", 
                            "totalperc": 0.24691358024691357, 
                            "disconnectperc": 0.0, 
                            "details": [
                                {
                                    "modulename": "Seçilen Tarifenin Detayını Dinleyenler", 
                                    "enddate": "", 
                                    "beginddate": "2018-05-10", 
                                    "totalcall": 1, 
                                    "totaldisconnect": 0, 
                                    "dtmf": "", 
                                    "totalhangup": 0, 
                                    "totalagent": 1, 
                                    "nodedesctag": "Tarife Info detay anonsu", 
                                    "totalperc": 25.0, 
                                    "disconnectperc": 0, 
                                    "details": [], 
                                    "agentperc": 50.0, 
                                    "hangupperc": 0.0
                                }, 
                                {
                                    "modulename": "Diğer (Ana Menü,Hangup, vs)", 
                                    "enddate": "", 
                                    "beginddate": "2018-05-10", 
                                    "totalcall": 4, 
                                    "totaldisconnect": 0, 
                                    "dtmf": "", 
                                    "totalhangup": 2, 
                                    "totalagent": 2, 
                                    "nodedesctag": "", 
                                    "totalperc": 100.0, 
                                    "disconnectperc": 0, 
                                    "details": [], 
                                    "agentperc": 100.0, 
                                    "hangupperc": 100.0
                                }
                            ], 
                            "agentperc": 0.12987012987012986, 
                            "hangupperc": 2.73972602739726
                        }, 
                        {
                            "modulename": "Tarifesini Değiştirenler", 
                            "enddate": "", 
                            "beginddate": "2018-05-10", 
                            "totalcall": 1620, 
                            "totaldisconnect": 7, 
                            "dtmf": "2", 
                            "totalhangup": 73, 
                            "totalagent": 1540, 
                            "nodedesctag": "", 
                            "totalperc": 100.0, 
                            "disconnectperc": 100.0, 
                            "details": [], 
                            "agentperc": 100.0, 
                            "hangupperc": 100.0
                        }, 
                        {
                            "modulename": "Diğer(Anamenü, Hangup, vb)", 
                            "enddate": "", 
                            "beginddate": "2018-05-10", 
                            "totalcall": 1620, 
                            "totaldisconnect": 7, 
                            "dtmf": "3", 
                            "totalhangup": 73, 
                            "totalagent": 1540, 
                            "nodedesctag": "", 
                            "totalperc": 100.0, 
                            "disconnectperc": 100.0, 
                            "details": [], 
                            "agentperc": 100.0, 
                            "hangupperc": 100.0
                        }
                    ], 
                    "agentperc": 21.859474804826117, 
                    "hangupperc": 2.569517775431186
                }, 
                {
                    "modulename": "Taahhüt İşlemleri", 
                    "enddate": "", 
                    "beginddate": "2018-05-10", 
                    "totalcall": 1107, 
                    "totaldisconnect": 20, 
                    "dtmf": "2", 
                    "totalhangup": 264, 
                    "totalagent": 823, 
                    "nodedesctag": "Tarife Alt MenuTaahudslemleri", 
                    "totalperc": 11.105537720706259, 
                    "disconnectperc": 24.390243902439025, 
                    "details": [], 
                    "agentperc": 11.682044002838893, 
                    "hangupperc": 9.292502639915522
                }, 
                {
                    "modulename": "Kalan Kullanım", 
                    "enddate": "", 
                    "beginddate": "2018-05-10", 
                    "totalcall": 2688, 
                    "totaldisconnect": 49, 
                    "dtmf": "3", 
                    "totalhangup": 2452, 
                    "totalagent": 187, 
                    "nodedesctag": "Tarife Alt MenuKalanKullanim", 
                    "totalperc": 26.96629213483146, 
                    "disconnectperc": 59.756097560975604, 
                    "details": [
                        {
                            "modulename": "Kalan Kullanım Detayını Dinleyenler", 
                            "enddate": "", 
                            "beginddate": "2018-05-10", 
                            "totalcall": 2193, 
                            "totaldisconnect": 40, 
                            "dtmf": "", 
                            "totalhangup": 2008, 
                            "totalagent": 145, 
                            "nodedesctag": "GuncelFaturaVeKullanim - Güncel Bilgilerin Tümünün Anonsu", 
                            "totalperc": 81.58482142857143, 
                            "disconnectperc": 81.63265306122449, 
                            "details": [
                                {
                                    "modulename": "Paket Sunulanlar", 
                                    "enddate": "", 
                                    "beginddate": "2018-05-10", 
                                    "totalcall": 167, 
                                    "totaldisconnect": 3, 
                                    "dtmf": "1", 
                                    "totalhangup": 122, 
                                    "totalagent": 42, 
                                    "nodedesctag": "Postpaid Yeni Paketler Transfer", 
                                    "totalperc": 7.615139078887369, 
                                    "disconnectperc": 7.5, 
                                    "details": [], 
                                    "agentperc": 28.965517241379313, 
                                    "hangupperc": 6.075697211155378
                                }
                            ], 
                            "agentperc": 77.54010695187165, 
                            "hangupperc": 81.89233278955955
                        }, 
                        {
                            "modulename": "Kalan Datası 0 Olanlar", 
                            "enddate": "", 
                            "beginddate": "2018-05-10", 
                            "totalcall": 73, 
                            "totaldisconnect": 4, 
                            "dtmf": "", 
                            "totalhangup": 55, 
                            "totalagent": 14, 
                            "nodedesctag": "GuncelFaturaVeKullanim - Bilgi Bulunamadı Anonsu", 
                            "totalperc": 2.7157738095238098, 
                            "disconnectperc": 8.16326530612245, 
                            "details": [
                                {
                                    "modulename": "Paket Sunulanlar", 
                                    "enddate": "", 
                                    "beginddate": "2018-05-10", 
                                    "totalcall": 13, 
                                    "totaldisconnect": 1, 
                                    "dtmf": "1", 
                                    "totalhangup": 7, 
                                    "totalagent": 5, 
                                    "nodedesctag": "Postpaid Yeni Paketler Transfer", 
                                    "totalperc": 17.80821917808219, 
                                    "disconnectperc": 25.0, 
                                    "details": [], 
                                    "agentperc": 35.714285714285715, 
                                    "hangupperc": 12.727272727272727
                                }
                            ], 
                            "agentperc": 7.4866310160427805, 
                            "hangupperc": 2.2430668841761827
                        }, 
                        {
                            "modulename": "FKT Nedeniyle Kalan Datası Bulunmayanlar", 
                            "enddate": "", 
                            "beginddate": "2018-05-10", 
                            "totalcall": 415, 
                            "totaldisconnect": 5, 
                            "dtmf": "", 
                            "totalhangup": 386, 
                            "totalagent": 24, 
                            "nodedesctag": "GuncelFaturaVeKullanim - CDR Kontrol Edilmeli Anonsu", 
                            "totalperc": 15.438988095238097, 
                            "disconnectperc": 10.204081632653061, 
                            "details": [
                                {
                                    "modulename": "Paket Sunulanlar", 
                                    "enddate": "", 
                                    "beginddate": "2018-05-10", 
                                    "totalcall": 15, 
                                    "totaldisconnect": 0, 
                                    "dtmf": "1", 
                                    "totalhangup": 11, 
                                    "totalagent": 4, 
                                    "nodedesctag": "Postpaid Yeni Paketler Transfer", 
                                    "totalperc": 3.614457831325301, 
                                    "disconnectperc": 0.0, 
                                    "details": [], 
                                    "agentperc": 16.666666666666664, 
                                    "hangupperc": 2.849740932642487
                                }
                            ], 
                            "agentperc": 12.834224598930483, 
                            "hangupperc": 15.742251223491028
                        }
                    ], 
                    "agentperc": 2.654364797728886, 
                    "hangupperc": 86.30763815557903
                }, 
                {
                    "modulename": "Yurtdışı Servisleri", 
                    "enddate": "", 
                    "beginddate": "2018-05-10", 
                    "totalcall": 112, 
                    "totaldisconnect": 5, 
                    "dtmf": "4", 
                    "totalhangup": 61, 
                    "totalagent": 46, 
                    "nodedesctag": "Tarife Alt Menu YurtDişiServisleri", 
                    "totalperc": 1.1235955056179776, 
                    "disconnectperc": 6.097560975609756, 
                    "details": [], 
                    "agentperc": 0.6529453513129879, 
                    "hangupperc": 2.1471312917986625
                }, 
                {
                    "modulename": "MT Transfer", 
                    "enddate": "", 
                    "beginddate": "2018-05-10", 
                    "totalcall": 4869, 
                    "totaldisconnect": 0, 
                    "dtmf": "0", 
                    "totalhangup": 6, 
                    "totalagent": 4863, 
                    "nodedesctag": "Tarife Menu Postpaid Alt Menusu , MT Transfer", 
                    "totalperc": 48.84630818619583, 
                    "disconnectperc": 0.0, 
                    "details": [], 
                    "agentperc": 69.02767920511, 
                    "hangupperc": 0.21119324181626187
                }
            ], 
            "agentperc": 34.786687734544735, 
            "hangupperc": 26.721218961625283
        }, 
        {
            "modulename": "Kampanyalar", 
            "enddate": "", 
            "beginddate": "2018-05-10", 
            "totalcall": 4133, 
            "totaldisconnect": 173, 
            "dtmf": "3", 
            "totalhangup": 742, 
            "totalagent": 3218, 
            "nodedesctag": "Postpaid Menu Kampayalar", 
            "totalperc": 12.951240912509402, 
            "disconnectperc": 16.828793774319067, 
            "details": [], 
            "agentperc": 15.889788662848115, 
            "hangupperc": 6.978931527464259
        }, 
        {
            "modulename": "Yeni Paketler", 
            "enddate": "", 
            "beginddate": "2018-05-10", 
            "totalcall": 4564, 
            "totaldisconnect": 45, 
            "dtmf": "4", 
            "totalhangup": 2421, 
            "totalagent": 2098, 
            "nodedesctag": "Postpaid Menu Yeni", 
            "totalperc": 14.30183003258962, 
            "disconnectperc": 4.3774319066147855, 
            "details": [], 
            "agentperc": 10.3594706695635, 
            "hangupperc": 22.770880361173816
        }, 
        {
            "modulename": "OTA", 
            "enddate": "", 
            "beginddate": "2018-05-10", 
            "totalcall": 2484, 
            "totaldisconnect": 90, 
            "dtmf": "5", 
            "totalhangup": 967, 
            "totalagent": 1427, 
            "nodedesctag": "Postpaid Menu OTA", 
            "totalperc": 7.783905740787164, 
            "disconnectperc": 8.754863813229571, 
            "details": [], 
            "agentperc": 7.046217657515307, 
            "hangupperc": 9.095184349134689
        }, 
        {
            "modulename": "Kayıp Çalıntı", 
            "enddate": "", 
            "beginddate": "2018-05-10", 
            "totalcall": 2311, 
            "totaldisconnect": 90, 
            "dtmf": "6", 
            "totalhangup": 693, 
            "totalagent": 1528, 
            "nodedesctag": "Postpaid Menu KayıpÇalıntı", 
            "totalperc": 7.241789922286287, 
            "disconnectperc": 8.754863813229571, 
            "details": [], 
            "agentperc": 7.5449338336954375, 
            "hangupperc": 6.518058690744921
        }, 
        {
            "modulename": "MT Transfer", 
            "enddate": "", 
            "beginddate": "2018-05-10", 
            "totalcall": 1639, 
            "totaldisconnect": 0, 
            "dtmf": "0", 
            "totalhangup": 1, 
            "totalagent": 1638, 
            "nodedesctag": "PostPaid Ana Menu , MT Transfer", 
            "totalperc": 5.1359989972424165, 
            "disconnectperc": 0.0, 
            "details": [], 
            "agentperc": 8.088090065178747, 
            "hangupperc": 0.009405568096313016
        }
    ], 
    "agentperc": 64.69460771786353, 
    "hangupperc": 40.74343744012263
}